ecb/__init__.py
ecb/constants.py
ecb/helpers.py
python_ecb_daily-0.3.dist-info/LICENSE
python_ecb_daily-0.3.dist-info/METADATA
python_ecb_daily-0.3.dist-info/WHEEL
python_ecb_daily-0.3.dist-info/top_level.txt
python_ecb_daily-0.3.dist-info/RECORD
