Metadata-Version: 2.1
Name: python-ecb-daily
Version: 0.3
Summary: Python ECB Daily Rates Wrapper
Home-page: https://github.com/fatihsucu/python-ecb-daily
Author: Fatih Sucu
Author-email: fatihsucu0@gmail.com
License: MIT
Platform: UNKNOWN
Requires-Dist: feedparser
